pandy/__init__.py
pandy-0.0a0.dist-info/LICENSE
pandy-0.0a0.dist-info/METADATA
pandy-0.0a0.dist-info/WHEEL
pandy-0.0a0.dist-info/top_level.txt
pandy-0.0a0.dist-info/RECORD
