Metadata-Version: 2.1
Name: pandy
Version: 0.0a0
Summary: Personal Python Handyman
Home-page: https://github.com/pypa/sampleproject
Author: Kammon
Author-email: takagate+pypi@gmail.com
License: UNKNOWN
Project-URL: Bug Tracker, https://github.com/pypa/sampleproject/issues
Platform: UNKNOWN
Classifier: Programming Language :: Python :: 3
Classifier: License :: OSI Approved :: MIT License
Classifier: Operating System :: OS Independent
Requires-Python: >=3.6
